{
  "users": [
    {
      "id": 1,
      "name": "Матвей",
      "city": "Казань",
      "birthDate": "1995-06-12",
      "gender": "male",
      "email": "matvei@example.com",
      "about": "Даже когда нет шансов, всегда есть шанс",
      "skillOfferedId": 1,
      "subcategoriesWanted": [6, 11],
      "favoritesSkills": [2],
      "createdAt": "2025-11-05T12:34:00Z",
      "updatedAt": "2025-12-05T12:34:00Z",
      "avatarUrl": "/images/users/default-avatar.png"
    },
    {
      "id": 2,
      "name": "Оленька",
      "city": "Казань",
      "birthDate": "1995-05-20",
      "gender": "female",
      "email": "olenka111@example.com",
      "about": "Иллюстратор, ищу людей для совместных проектов",
      "skillOfferedId": 2,
      "subcategoriesWanted": [1, 11],
      "favoritesSkills": [1],
      "createdAt": "2025-01-12T09:20:00Z",
      "updatedAt": "2025-02-05T12:34:00Z",
      "avatarUrl": "/images/users/default-avatar.png"
    },
    {
      "id": 3,
      "name": "Борис",
      "city": "Казань",
      "birthDate": "2015-01-31",
      "gender": "male",
      "email": "borusss@example.com",
      "about": "Путешествия — моя жизнь",
      "skillOfferedId": 3,
      "subcategoriesWanted": [1, 6],
      "favoritesSkills": [1, 2],
      "createdAt": "2025-03-12T09:20:00Z",
      "updatedAt": "2025-04-05T12:34:00Z",
      "avatarUrl": "/images/users/default-avatar.png"
    }
  ]
}
